alert_from_script
