Metadata-Version: 1.0
Name: alert-from-script
Version: 0.1.2
Summary: Generate SNS alerts from any command.
Home-page: https://github.com/adamsb6/alert_from_script
Author: Brandon Adams
Author-email: brandon.adams@me.com
License: UNKNOWN
Platform: UNKNOWN
